[
  {
    "title": "20% de remise immédiate sur une sélection de LEGOS. Ex: LEGO Technic 42171 - Mercedes-AMG F1 W14 E Performance, 1642 pièces",
    "link": "https://www.dealabs.com/bons-plans/20-de-remise-immediate-sur-une-selection-de-lego-ex-lego-technic-mercedes-amg-f1-w14-e-performance-42171-1642-pieces-3016242",
    "price": 151.99,
    "commentCount": 0,
    "temperature": 11.7,
    "publishedDate": 1741612492
  },
  {
    "title": "LEGO Art 31212 - La Voie Lactée",
    "link": "https://www.dealabs.com/bons-plans/lego-art-31212-la-voie-lactee-3016236",
    "price": 159.99,
    "commentCount": 1,
    "temperature": 25.02,
    "publishedDate": 1741611767
  },
  {
    "title": "Jeu de construction Lego Technic La Moto Ducati Panigale V4 S - 42202 (via cagnottage)",
    "link": "https://www.dealabs.com/bons-plans/lego-technic-42202-la-moto-ducati-panigale-v4-s-via-cagnottage-3016235",
    "price": 119.99,
    "commentCount": 0,
    "temperature": 27.98,
    "publishedDate": 1741611689
  },
  {
    "title": "LEGO Art 31213 - La Joconde Mona Lisa (19,99€ via Cagnottage)",
    "link": "https://www.dealabs.com/bons-plans/lego-art-31213-la-joconde-mona-lisa-via-cagnottage-3016234",
    "price": 59.99,
    "commentCount": 0,
    "temperature": 21.78,
    "publishedDate": 1741611625
  },
  {
    "title": "[Precommande] Mario Kart LEGO Super Mario (72037) 1972 pièces (+ minifigure customisée \"Easter Wolf\" OFFERT)",
    "link": "https://www.dealabs.com/bons-plans/precommande-mario-kart-lego-super-mario-72037-1972-pieces-minifigure-customisee-easter-wolf-offert-3016205",
    "price": 144.49,
    "commentCount": 3,
    "temperature": 57.06,
    "publishedDate": 1741608935
  },
  {
    "title": "Offre Mario Day Lego : le set Lego Mario Kart – Toad stand (30702) offert pour tout achat sur une sélection",
    "link": "https://www.dealabs.com/bons-plans/offre-mario-day-lego-le-set-lego-mario-kart-toad-stand-30702-offert-pour-tout-achat-sur-une-selection-3016139",
    "price": 0,
    "commentCount": 6,
    "temperature": 92.93,
    "publishedDate": 1741600407
  },
  {
    "title": "LEGO 76435 Harry Potter Le Château de Poudlard : la Grande Salle",
    "link": "https://www.dealabs.com/bons-plans/lego-76435-harry-potter-le-chateau-de-poudlard-la-grande-salle-3016055",
    "price": 134.66,
    "commentCount": 0,
    "temperature": 26.46,
    "publishedDate": 1741594963
  },
  {
    "title": "Lego City 60453 - Le véhicule de secours de la plage (via 5,75€ cagnotté)",
    "link": "https://www.dealabs.com/bons-plans/lego-city-60453-le-vehicule-de-secours-de-la-plage-via-cagnottage-3016046",
    "price": 17.24,
    "commentCount": 0,
    "temperature": 20.53,
    "publishedDate": 1741594513
  },
  {
    "title": "Lego Mario Kart 72032 - Kart Standard (via 4,5€ cagnottage)",
    "link": "https://www.dealabs.com/bons-plans/mario-kart-72032-kart-standard-via-cagnottage-3016045",
    "price": 13.49,
    "commentCount": 0,
    "temperature": 39.77,
    "publishedDate": 1741594415
  },
  {
    "title": "Lego Super Mario 71437 : The Bowser Express Train (via 25€ cagnotté)",
    "link": "https://www.dealabs.com/bons-plans/le-train-bowser-express-lego-super-mario-71437-the-bowser-express-train-via-cagnottage-3016044",
    "price": 74.99,
    "commentCount": 0,
    "temperature": 21.22,
    "publishedDate": 1741594333
  },
  {
    "title": "Lego City 60444 - Garage de F1et voitures Mercedes AMG et Alpine (via 17,5€ cagnottés)",
    "link": "https://www.dealabs.com/bons-plans/city-60444-garage-de-f1et-voitures-mercedes-amg-et-alpine-via-cagnottage-3016040",
    "price": 52.49,
    "commentCount": 0,
    "temperature": 18.99,
    "publishedDate": 1741594081
  },
  {
    "title": "1 Lego Mario acheté, le 2ème à 50% de réduction parmi une sélection",
    "link": "https://www.dealabs.com/codes-promo/1-lego-mario-achete-le-2e-a-50-3016021",
    "price": 0,
    "commentCount": 5,
    "temperature": 64.12,
    "publishedDate": 1741592076
  },
  {
    "title": "25% de remise sur une sélection de Lego - Ex: Lego Super Mario 71438 - Super Mario World Mario & Yoshi (via 26.75€ cagnotté)",
    "link": "https://www.dealabs.com/bons-plans/25-de-cagnottage-sur-une-selection-de-lego-exsuper-mario-71438-super-mario-world-mario-yoshi-3015985",
    "price": 80.24,
    "commentCount": 18,
    "temperature": 324.99,
    "publishedDate": 1741585935
  },
  {
    "title": "Sélection de lego Mario remisés à 25% sur carte Leclerc",
    "link": "https://www.dealabs.com/bons-plans/selection-de-lego-remises-a-25-sur-carte-leclerc-3015966",
    "price": 0,
    "commentCount": 4,
    "temperature": 31.57,
    "publishedDate": 1741572085
  },
  {
    "title": "Lego Technic 42158 - Nasa Mars Rover Persévérance, Avec AR App Expérience (via 18,25€ cagnotté)",
    "link": "https://www.dealabs.com/bons-plans/lego-technic-42158-nasa-mars-rover-perseverance-avec-ar-app-experience-decouverte-de-la-science-et-de-lespace-via-cagnottage-3015964",
    "price": 54.74,
    "commentCount": 0,
    "temperature": 25.65,
    "publishedDate": 1741571106
  },
  {
    "title": "Lego Super Mario 71411 Le Puissant Bowser (via 52,50€ cagnotté)",
    "link": "https://www.dealabs.com/bons-plans/lego-super-mario-71411-le-puissant-bowser-via-cagnottage-3015963",
    "price": 157.49,
    "commentCount": 7,
    "temperature": 41.66,
    "publishedDate": 1741571000
  },
  {
    "title": "Sélection de lego en promotion, ex LEGO City Camion de F1 avec voitures de F1 RB20 et AMR24 - 60445",
    "link": "https://www.dealabs.com/bons-plans/selection-de-lego-en-promotion-ex-lego-city-camion-de-f1-avec-voitures-de-f1-rb20-et-amr24-60445-3015820",
    "price": 64.53,
    "commentCount": 2,
    "temperature": 7.1,
    "publishedDate": 1741541238
  },
  {
    "title": "LEGO Marvel Collection sur PS4 (dématérialisé)",
    "link": "https://www.dealabs.com/bons-plans/lego-marvel-collection-3015589",
    "price": 7.79,
    "commentCount": 0,
    "temperature": 44.74,
    "publishedDate": 1741509477
  },
  {
    "title": "LEGO Speed Champions 76919 - La Voiture de Course de Formule 1 McLaren 2023",
    "link": "https://www.dealabs.com/bons-plans/lego-speed-champions-la-voiture-de-course-de-formule-1-mclaren-2023-3015577",
    "price": 17.99,
    "commentCount": 5,
    "temperature": 75.42,
    "publishedDate": 1741508742
  },
  {
    "title": "LEGO Architecture 21061 : Notre-Dame de Paris",
    "link": "https://www.dealabs.com/bons-plans/lego-architecture-notre-dame-de-paris-3015552",
    "price": 171.06,
    "commentCount": 5,
    "temperature": -64.55,
    "publishedDate": 1741506008
  },
  {
    "title": "LEGO Fortnite 77071 - Lama de ravitaillement",
    "link": "https://www.dealabs.com/bons-plans/lego-fortnite-lama-de-ravitaillement-3015548",
    "price": 30.99,
    "commentCount": 0,
    "temperature": 44.61,
    "publishedDate": 1741505671
  },
  {
    "title": "Lego Fortnite 77073 Autobus de Combat",
    "link": "https://www.dealabs.com/bons-plans/lego-fortnite-autobus-de-combat-ensemble-de-construction-pour-fans-3015542",
    "price": 74.38,
    "commentCount": 0,
    "temperature": 22.48,
    "publishedDate": 1741504951
  },
  {
    "title": "The Lego Ninjago Movie Video Game sur PC (dématérialisé)",
    "link": "https://www.dealabs.com/bons-plans/the-lego-ninjago-movie-video-game-3015299",
    "price": 1.2,
    "commentCount": 0,
    "temperature": 25.82,
    "publishedDate": 1741446697
  },
  {
    "title": "LEGO Star Wars (75405) - Starcruiser Home One (via 14,98€ sur Carte de Fidélité)",
    "link": "https://www.dealabs.com/bons-plans/lego-star-wars-75405-starcruiser-home-one-via-1498eur-sur-carte-de-fidelite-3015267",
    "price": 44.92,
    "commentCount": 0,
    "temperature": 82.01,
    "publishedDate": 1741443365
  },
  {
    "title": "LEGO Technic 42172 - McLaren P1 (78,25€ via Cagnottage - Frontaliers Luxembourg)",
    "link": "https://www.dealabs.com/bons-plans/lego-technic-mclaren-p1-42172-78eur-en-cagnotte-3015177",
    "price": 234.75,
    "commentCount": 10,
    "temperature": 331.19,
    "publishedDate": 1741429411
  },
  {
    "title": "Jouet Lego Disney Princess Heihei Vaiana 2 43272 (Frontaliers Belgique)",
    "link": "https://www.dealabs.com/bons-plans/lego-disney-princess-heihei-vaiana-2-43272-frontaliers-belges-uniquement-3015161",
    "price": 29.95,
    "commentCount": 3,
    "temperature": 237.55,
    "publishedDate": 1741427700
  },
  {
    "title": "LEGO Marvel 76291 - Avengers Rassemblement : L’ère d’Ultron (19.25€ via Cagnottage)",
    "link": "https://www.dealabs.com/bons-plans/lego-marvel-76291-avengers-rassemblement-lere-dultron-via-1925eur-en-tickets-eleclerc-3015133",
    "price": 57.74,
    "commentCount": 3,
    "temperature": 36.68,
    "publishedDate": 1741424783
  },
  {
    "title": "Lego Technic 42174 : Yacht Emirates Team New Zealand AC75",
    "link": "https://www.dealabs.com/bons-plans/yacht-emirates-team-new-zealand-ac75-3014681",
    "price": 74.99,
    "commentCount": 1,
    "temperature": 95.51,
    "publishedDate": 1741354731
  },
  {
    "title": "Lego 10338 : Bumblebee Transformers",
    "link": "https://www.dealabs.com/bons-plans/lego-bumblebee-transformers-3014679",
    "price": 52.5,
    "commentCount": 4,
    "temperature": 230.88,
    "publishedDate": 1741354573
  },
  {
    "title": "Lego Technic 42182 Véhicule d’exploration lunaire NASA Apollo - LRV (Via 41,07€ sur la Carte de Fidélité)",
    "link": "https://www.dealabs.com/bons-plans/vehicule-dexploration-lunaire-nasa-apollo-lrv-3014676",
    "price": 123.29,
    "commentCount": 1,
    "temperature": 54.94,
    "publishedDate": 1741354384
  }
]